libre_link_up/__init__.py
libre_link_up/client.py
libre_link_up/custom_types.py
libre_linkup_py-0.2.5.dist-info/METADATA
libre_linkup_py-0.2.5.dist-info/WHEEL
libre_linkup_py-0.2.5.dist-info/licenses/LICENSE
libre_linkup_py-0.2.5.dist-info/RECORD
