Metadata-Version: 2.4
Name: libre-linkup-py
Version: 0.2.5
Summary: Unofficial libre linkup python client
Author-email: Sam Purkis <sam.purkis@hotmail.co.uk>
License-File: LICENSE
Requires-Python: >=3.9
Requires-Dist: python-dotenv>=1.0.1
Requires-Dist: pytz>=2024.1
Requires-Dist: requests>=2.31.0
